{
  "spacing": {
    "none": { "$value": "{scale.0}", "$type": "dimension" },
    "xs": { "$value": "{scale.1}", "$type": "dimension" },
    "sm": { "$value": "{scale.2}", "$type": "dimension" },
    "md": { "$value": "{scale.3}", "$type": "dimension" },
    "lg": { "$value": "{scale.4}", "$type": "dimension" },
    "xl": { "$value": "{scale.6}", "$type": "dimension" },
    "2xl": { "$value": "{scale.8}", "$type": "dimension" },
    "3xl": { "$value": "{scale.12}", "$type": "dimension" },
    "4xl": { "$value": "{scale.16}", "$type": "dimension" }
  }
}
